{
  "name": "Вентилятор канальный ВКК 160М Logifan , производительность 900 м3/час",
  "specs": {
    "Тип": "Вентилятор канальный",
    "Сечение воздуховода, мм": "160x160",
    "Диаметр воздуховода, мм": "160",
    "Вид работы вентилятора": "Приточно-вытяжной",
    "Потребляемая мощность, Вт": "160",
    "Оплатить позже": "Без % до 10 сентября",
    "Артикул": "2775505619"
  },
  "images": [
    "images/01_7872244486.jpg",
    "images/02_7872245410.jpg",
    "images/03_7872244882.jpg",
    "images/04_7861463495.jpg",
    "images/05_7873815736.jpg"
  ]
}