{
  "name": "Вентилятор осевой вытяжной на квадратной пластине Серия YWF-2Е 300B",
  "price": 6532,
  "price_original": 7218,
  "rating": 5.0,
  "reviews_count": 1,
  "description": "Промышленный вытяжной осевой вентилятор — это устройство, созданное для эффективного удаления воздуха из складских помещений и ангаров. Оно обеспечивает поддержание оптимального микроклимата в этих пространствах, что является важным фактором для сохранения качества товаров и обеспечения комфортных условий работы персонала.Вентиляторы доступны в различных диаметрах лопастей и способны перемещать разное количество воздуха в зависимости от модели. Это позволяет подобрать оптимальный вариант для конкретных потребностей и размеров помещения.Основные преимущества промышленных вытяжных осевых вентиляторов включают:Высокая производительность: благодаря своей конструкции и мощным двигателям, эти вентиляторы способны быстро и эффективно удалять воздух из помещений.Надежность: они изготовлены из качественных материалов, что обеспечивает долгий срок службы.Простота в эксплуатации: вентиляторы легко устанавливаются и обслуживаются, что делает их удобными в использовании.Промышленные вытяжные осевые вентиляторы — незаменимое оборудование для складов и ангаров, где требуется эффективная вентиляция и поддержание оптимального микроклимата.",
  "specs": {
    "Тип": "Вентилятор приточно-вытяжной",
    "Диаметр воздуховода, мм": "300",
    "Рабочий механизм вентилятора": "Осевой",
    "Установка вентиляции": "Накладной",
    "Вид работы вентилятора": "Приточно-вытяжной",
    "Оплатить позже": "Без % до 10 сентября",
    "Артикул": "2816266849"
  },
  "images": [
    "images/01_logo_ozon_1.png",
    "images/02_7140483203.jpg",
    "images/03_6869606184.jpg",
    "images/04_6869606175.jpg",
    "images/05_7114969983.jpg",
    "images/06_7140483203.jpg",
    "images/07_postPaymentAll.png",
    "images/08_7140483203.jpg",
    "images/09_7140483203.jpg",
    "images/10_9J83YBPQlt9zlECcAVvZ8sT55b0jRguK.png",
    "images/11_qr-code_1.png"
  ]
}