{
  "name": "Вентилятор канальный ВКК 250М Logifan , производительность 1150 м3/час",
  "specs": {
    "Тип": "Вентилятор канальный",
    "Сечение воздуховода, мм": "250x250",
    "Диаметр воздуховода, мм": "250",
    "Вид работы вентилятора": "Приточно-вытяжной",
    "Оплатить позже": "Без % до 10 сентября",
    "Артикул": "2775521044"
  },
  "images": [
    "images/01_7872244486.jpg",
    "images/02_7872245410.jpg",
    "images/03_7872244882.jpg",
    "images/04_7861463495.jpg",
    "images/05_7873815736.jpg"
  ]
}